{
  "tasks": [
    {
      "CPU": 8,
      "RAM": 32,
      "allocatedOn": 0
    },
    {
      "CPU": 10,
      "RAM": 16,
      "allocatedOn": 0
    },
    {
      "CPU": 2,
      "RAM": 1,
      "allocatedOn": 1
    },
    {
      "CPU": 8,
      "RAM": 16,
      "allocatedOn": 1
    },
    {
      "CPU": 1,
      "RAM": 1,
      "allocatedOn": 1
    },
    {
      "CPU": 1,
      "RAM": 1,
      "allocatedOn": 1
    },
    {
      "CPU": 8,
      "RAM": 24,
      "allocatedOn": 2
    },
    {
      "CPU": 1,
      "RAM": 1,
      "allocatedOn": 2
    },
    {
      "CPU": 2,
      "RAM": 1,
      "allocatedOn": 2
    },
    {
      "CPU": 1,
      "RAM": 1,
      "allocatedOn": 2
    },
    {
      "CPU": 8,
      "RAM": 24,
      "allocatedOn": 3
    },
    {
      "CPU": 1,
      "RAM": 1,
      "allocatedOn": 3
    },
    {
      "CPU": 1,
      "RAM": 1,
      "allocatedOn": 3
    },
    {
      "CPU": 4,
      "RAM": 8,
      "allocatedOn": 3
    },
    {
      "CPU": 8,
      "RAM": 16,
      "allocatedOn": 4
    },
    {
      "CPU": 4,
      "RAM": 8,
      "allocatedOn": 4
    },
    {
      "CPU": 10,
      "RAM": 48,
      "allocatedOn": 5
    },
    {
      "CPU": 10,
      "RAM": 16,
      "allocatedOn": 6
    },
    {
      "CPU": 8,
      "RAM": 8,
      "allocatedOn": 7
    },
    {
      "CPU": 1,
      "RAM": 1,
      "allocatedOn": 8
    },
    {
      "CPU": 8,
      "RAM": 10,
      "allocatedOn": 8
    },
    {
      "CPU": 2,
      "RAM": 4,
      "allocatedOn": 9
    },
    {
      "CPU": 1,
      "RAM": 1,
      "allocatedOn": 9
    },
    {
      "CPU": 1,
      "RAM": 1,
      "allocatedOn": 9
    },
    {
      "CPU": 1,
      "RAM": 1,
      "allocatedOn": 9
    },
    {
      "CPU": 1,
      "RAM": 1,
      "allocatedOn": 9
    },
    {
      "CPU": 1,
      "RAM": 1,
      "allocatedOn": 9
    },
    {
      "CPU": 1,
      "RAM": 1,
      "allocatedOn": 10
    },
    {
      "CPU": 1,
      "RAM": 2,
      "allocatedOn": 10
    },
    {
      "CPU": 1,
      "RAM": 2,
      "allocatedOn": 10
    },
    {
      "CPU": 1,
      "RAM": 1,
      "allocatedOn": 10
    },
    {
      "CPU": 1,
      "RAM": 2,
      "allocatedOn": 10
    },
    {
      "CPU": 1,
      "RAM": 1,
      "allocatedOn": 10
    },
    {
      "CPU": 1,
      "RAM": 1,
      "allocatedOn": 11
    },
    {
      "CPU": 1,
      "RAM": 2,
      "allocatedOn": 11
    },
    {
      "CPU": 1,
      "RAM": 1,
      "allocatedOn": 11
    },
    {
      "CPU": 2,
      "RAM": 4,
      "allocatedOn": 11
    },
    {
      "CPU": 1,
      "RAM": 1,
      "allocatedOn": 11
    },
    {
      "CPU": 2,
      "RAM": 4,
      "allocatedOn": 12
    },
    {
      "CPU": 1,
      "RAM": 1,
      "allocatedOn": 12
    },
    {
      "CPU": 2,
      "RAM": 4,
      "allocatedOn": 13
    },
    {
      "CPU": 1,
      "RAM": 1,
      "allocatedOn": 13
    },
    {
      "CPU": 2,
      "RAM": 1,
      "allocatedOn": 14
    },
    {
      "CPU": 1,
      "RAM": 2,
      "allocatedOn": 15
    },
    {
      "CPU": 4,
      "RAM": 8,
      "allocatedOn": 15
    },
    {
      "CPU": 2,
      "RAM": 4,
      "allocatedOn": 15
    },
    {
      "CPU": 12,
      "RAM": 16,
      "allocatedOn": 15
    }
  ]
}